README.md
setup.cfg
setup.py
lib/toute/__init__.py
lib/toute/document.py
lib/toute/embedded_document.py
lib/toute/exceptions.py
lib/toute/fields.py
lib/toute/mapping.py
lib/toute.egg-info/PKG-INFO
lib/toute.egg-info/SOURCES.txt
lib/toute.egg-info/dependency_links.txt
lib/toute.egg-info/not-zip-safe
lib/toute.egg-info/requires.txt
lib/toute.egg-info/top_level.txt
lib/toute/bases/__init__.py
lib/toute/bases/document.py
lib/toute/bases/field.py
lib/toute/bases/metaclass.py
lib/toute/bases/py3.py
lib/toute/bases/result.py
lib/toute/utils/__init__.py
lib/toute/utils/example.py
lib/toute/utils/pagination.py
lib/toute/utils/validation.py
lib/toute/utils/payload/__init__.py
lib/toute/utils/payload/aggregates.py
lib/toute/utils/payload/base.py
lib/toute/utils/payload/exception.py
lib/toute/utils/payload/filters.py
lib/toute/utils/payload/meta.py
lib/toute/utils/payload/meta_util.py
lib/toute/utils/payload/queries.py
lib/toute/utils/payload/suggesters.py